create_discord_bot/__init__.py
create_discord_bot/main.py
create_discord_bot/boilerplates/__init__.py
create_discord_bot/boilerplates/bot_with_cogs.py
create_discord_bot/boilerplates/bot_without_cogs.py
create_discord_bot/boilerplates/env.py
create_discord_bot/boilerplates/requirements.py
create_discord_bot/boilerplates/sample_cog.py
bootstrap_discord_bot-1.2.0.dist-info/LICENSE
bootstrap_discord_bot-1.2.0.dist-info/METADATA
bootstrap_discord_bot-1.2.0.dist-info/WHEEL
bootstrap_discord_bot-1.2.0.dist-info/entry_points.txt
bootstrap_discord_bot-1.2.0.dist-info/top_level.txt
bootstrap_discord_bot-1.2.0.dist-info/RECORD
