Metadata-Version: 2.1
Name: bootstrap-discord-bot
Version: 1.2.0
Summary: An opinionated discord.py bot code bootstrapper
Home-page: https://github.com/Pradeep-selva/bootstrap-discord-bot
Author: pradeep-selva
Author-email: pradeep.selva8833@gmail.com
License: MIT
Keywords: discord.py cli-tool bootstrapper boilerplate code generator discord bot
Platform: UNKNOWN
Classifier: Programming Language :: Python :: 3
Classifier: Programming Language :: Python
Classifier: Programming Language :: Python :: 3
Classifier: Programming Language :: Python :: 3.4
Classifier: Programming Language :: Python :: 3.5
Classifier: Programming Language :: Python :: 3.6
Classifier: Programming Language :: Python :: 3.7
Classifier: Programming Language :: Python :: 3.8
Classifier: License :: OSI Approved :: MIT License
Classifier: Operating System :: OS Independent
Requires-Dist: argparse
